Metadata-Version: 1.0
Name: Amkdev-mia-tools
Version: 1.0.0
Summary: Python library To AI Students
Home-page: UNKNOWN
Author: ALLAOUI MOHAMED KHALIL
Author-email: UNKNOWN
License: MIT
Platform: UNKNOWN
